mpltWrappers/__init__.py
mpltWrappers/colorFuncs.py
mpltWrappers/colorPlots.py
mpltWrappers/figCreate.py
mpltWrappers/linePlots.py
mpltWrappers/plotSettings.py
mpltWrappers-0.0.1.dist-info/METADATA
mpltWrappers-0.0.1.dist-info/WHEEL
mpltWrappers-0.0.1.dist-info/top_level.txt
mpltWrappers-0.0.1.dist-info/RECORD
